msgraphy/__init__.py
msgraphy/api.py
msgraphy/auth/__init__.py
msgraphy/auth/config.py
msgraphy/auth/graph_auth.py
msgraphy/cli/__commands.py
msgraphy/cli/__init__.py
msgraphy/cli/__settings.py
msgraphy/client/__init__.py
msgraphy/client/graph_batch.py
msgraphy/client/graph_client.py
msgraphy/data/__init__.py
msgraphy/data/file.py
msgraphy/data/group.py
msgraphy/data/identity.py
msgraphy/data/list.py
msgraphy/data/monitor.py
msgraphy/data/sharepoint.py
msgraphy/data/site_page.py
msgraphy/data/team.py
msgraphy/data/user.py
msgraphy/data/workbook.py
msgraphy/domains/__init__.py
msgraphy/domains/files.py
msgraphy/domains/group.py
msgraphy/domains/list.py
msgraphy/domains/monitor.py
msgraphy/domains/sharepoint.py
msgraphy/domains/team.py
msgraphy/domains/user.py
msgraphy/domains/workbook.py
msgraphy/fs/__init__.py
msgraphy/fs/onedrivefs.py
msgraphy/fs/opener.py
msgraphy/sharepoint_classic/__init__.py
msgraphy-0.4.0.dist-info/LICENSE
msgraphy-0.4.0.dist-info/METADATA
msgraphy-0.4.0.dist-info/WHEEL
msgraphy-0.4.0.dist-info/entry_points.txt
msgraphy-0.4.0.dist-info/RECORD
