Metadata-Version: 2.1
Name: msgraphy
Version: 0.4.0
Summary: An API generator for the MS Graph API
License: MIT
Author: Kaj Siebert
Author-email: kaj@k-si.com
Requires-Python: >=3.7,<4
Classifier: License :: OSI Approved :: MIT License
Classifier: Programming Language :: Python :: 3
Classifier: Programming Language :: Python :: 3.7
Classifier: Programming Language :: Python :: 3.8
Classifier: Programming Language :: Python :: 3.9
Classifier: Programming Language :: Python :: 3.10
Classifier: Programming Language :: Python :: 3.11
Provides-Extra: cli
Provides-Extra: fs
Requires-Dist: click (>=8.1.3,<9.0.0) ; extra == "cli"
Requires-Dist: click-log (>=0.4.0,<0.5.0) ; extra == "cli"
Requires-Dist: fs.onedrivefs (>=1.1.1,<2.0.0) ; extra == "fs"
Requires-Dist: msal (>=1.10.0,<2.0.0)
Requires-Dist: pyhumps (>=3.0.2,<4.0.0)
Requires-Dist: requests (>=2.25.1,<3.0.0)
Requires-Dist: rich (>=12.6.0,<13.0.0) ; extra == "cli"
Requires-Dist: usersettings (>=1.1.5,<2.0.0) ; extra == "cli"
